python_developer_tools/__init__.py
python_developer_tools/web.py
python_developer_tools/cv/__init__.py
python_developer_tools/cv/common.py
python_developer_tools/cv/opencv_utils.py
python_developer_tools/cv/torch_utils.py
python_developer_tools/files/__init__.py
python_developer_tools/files/common.py
python_developer_tools/files/image_utils.py
python_developer_tools/files/txt_utils.py
python_developer_tools/files/xml_utils.py
python_developer_tools/python/__init__.py
python_developer_tools/python/obj_utils.py
python_developer_tools/python/string_utils.py
python_developer_tools/python/time_utils.py
python_developer_tools/python/tuple_utils.py
python_developer_tools-0.0.2.dist-info/LICENSE
python_developer_tools-0.0.2.dist-info/METADATA
python_developer_tools-0.0.2.dist-info/WHEEL
python_developer_tools-0.0.2.dist-info/top_level.txt
python_developer_tools-0.0.2.dist-info/RECORD
